{ "compressionlevel":-1,
 "height":17,
 "infinite":false,
 "layers":[
        {
         "draworder":"topdown",
         "id":7,
         "name":"lights",
         "objects":[
                {
                 "height":539,
                 "id":2,
                 "name":"",
                 "rotation":0,
                 "type":"",
                 "visible":true,
                 "width":603,
                 "x":3,
                 "y":3
                }],
         "opacity":1,
         "type":"objectgroup",
         "visible":true,
         "x":0,
         "y":0
        }, 
        {
         "draworder":"topdown",
         "id":5,
         "name":"doors",
         "objects":[
                {
                 "height":24,
                 "id":1,
                 "name":"",
                 "properties":[
                        {
                         "name":"dest_map",
                         "type":"string",
                         "value":"pallet_house1_f1"
                        }, 
                        {
                         "name":"dest_x",
                         "type":"int",
                         "value":13
                        }, 
                        {
                         "name":"dest_y",
                         "type":"int",
                         "value":6
                        }],
                 "rotation":0,
                 "type":"",
                 "visible":true,
                 "width":22,
                 "x":392,
                 "y":197
                }],
         "opacity":1,
         "type":"objectgroup",
         "visible":true,
         "x":0,
         "y":0
        }, 
        {
         "data":[0, 0, 0, 0, 0, 0, 0, 0, 0, 0, 0, 0, 0, 0, 0, 0, 0, 0, 0,
            0, 0, 0, 0, 0, 0, 0, 0, 0, 0, 0, 0, 0, 0, 0, 0, 0, 0, 0,
            0, 0, 0, 0, 0, 0, 0, 0, 0, 0, 0, 0, 0, 0, 0, 0, 0, 0, 0,
            0, 0, 0, 0, 0, 0, 0, 0, 0, 0, 0, 0, 0, 0, 0, 0, 0, 0, 0,
            0, 0, 0, 0, 386, 377, 377, 377, 377, 377, 377, 377, 377, 377, 377, 0, 0, 0, 0,
            0, 0, 0, 0, 386, 377, 377, 377, 377, 377, 377, 377, 377, 377, 377, 0, 0, 0, 0,
            0, 0, 0, 0, 386, 386, 386, 386, 386, 386, 386, 386, 386, 386, 386, 0, 0, 0, 0,
            0, 0, 0, 0, 386, 377, 377, 377, 377, 377, 377, 386, 386, 387, 377, 0, 0, 0, 0,
            0, 0, 0, 0, 386, 377, 377, 377, 377, 377, 377, 377, 377, 377, 377, 0, 0, 0, 0,
            0, 0, 0, 0, 386, 377, 377, 377, 794, 794, 794, 377, 377, 377, 377, 0, 0, 0, 0,
            0, 0, 0, 0, 386, 377, 377, 377, 794, 794, 794, 377, 377, 377, 377, 0, 0, 0, 0,
            0, 0, 0, 0, 386, 377, 377, 377, 377, 377, 377, 377, 377, 377, 377, 0, 0, 0, 0,
            0, 0, 0, 0, 386, 377, 377, 377, 377, 377, 377, 377, 377, 377, 377, 0, 0, 0, 0,
            0, 0, 0, 0, 0, 0, 0, 0, 0, 0, 0, 0, 0, 0, 0, 0, 0, 0, 0,
            0, 0, 0, 0, 0, 0, 0, 0, 0, 0, 0, 0, 0, 0, 0, 0, 0, 0, 0,
            0, 0, 0, 0, 0, 0, 0, 0, 0, 0, 0, 0, 0, 0, 0, 0, 0, 0, 0,
            0, 0, 0, 0, 0, 0, 0, 0, 0, 0, 0, 0, 0, 0, 0, 0, 0, 0, 0],
         "height":17,
         "id":1,
         "name":"floor",
         "opacity":1,
         "type":"tilelayer",
         "visible":true,
         "width":19,
         "x":0,
         "y":0
        }, 
        {
         "data":[0, 0, 0, 0, 0, 0, 0, 0, 0, 0, 0, 0, 0, 0, 0, 0, 0, 0, 0,
            0, 0, 0, 0, 0, 0, 0, 0, 0, 0, 0, 0, 0, 0, 0, 0, 0, 0, 0,
            0, 0, 0, 0, 0, 0, 0, 0, 0, 0, 0, 0, 0, 0, 0, 0, 0, 0, 0,
            0, 0, 0, 0, 0, 0, 0, 0, 0, 0, 0, 0, 0, 0, 0, 0, 0, 0, 0,
            0, 0, 0, 0, 0, 0, 0, 0, 0, 0, 0, 0, 0, 0, 0, 0, 0, 0, 0,
            0, 0, 0, 0, 41, 0, 0, 0, 0, 0, 0, 879, 0, 0, 0, 0, 0, 0, 0,
            0, 0, 0, 0, 1553, 1555, 1181, 1137, 1138, 0, 0, 887, 888, 904, 0, 0, 0, 0, 0,
            0, 0, 0, 0, 0, 0, 0, 0, 0, 0, 0, 895, 896, 912, 0, 0, 0, 0, 0,
            0, 0, 0, 0, 0, 0, 0, 785, 786, 786, 786, 787, 0, 0, 0, 0, 0, 0, 0,
            0, 0, 0, 0, 1209, 0, 1211, 793, 794, 1340, 794, 795, 0, 0, 0, 0, 0, 0, 0,
            0, 0, 0, 0, 1217, 0, 1219, 793, 794, 1348, 794, 795, 0, 0, 0, 0, 0, 0, 0,
            0, 0, 0, 0, 0, 0, 0, 801, 802, 802, 802, 803, 0, 0, 0, 0, 0, 0, 0,
            0, 0, 0, 0, 0, 0, 0, 0, 0, 0, 0, 0, 0, 0, 0, 0, 0, 0, 0,
            0, 0, 0, 0, 0, 0, 0, 0, 0, 0, 0, 0, 0, 0, 0, 0, 0, 0, 0,
            0, 0, 0, 0, 0, 0, 0, 0, 0, 0, 0, 0, 0, 0, 0, 0, 0, 0, 0,
            0, 0, 0, 0, 0, 0, 0, 0, 0, 0, 0, 0, 0, 0, 0, 0, 0, 0, 0,
            0, 0, 0, 0, 0, 0, 0, 0, 0, 0, 0, 0, 0, 0, 0, 0, 0, 0, 0],
         "height":17,
         "id":2,
         "name":"grass",
         "opacity":1,
         "type":"tilelayer",
         "visible":true,
         "width":19,
         "x":0,
         "y":0
        }, 
        {
         "data":[0, 0, 0, 0, 0, 0, 0, 0, 0, 0, 0, 0, 0, 0, 0, 0, 0, 0, 0,
            0, 0, 0, 0, 0, 0, 0, 0, 0, 0, 0, 0, 0, 0, 0, 0, 0, 0, 0,
            0, 0, 0, 0, 0, 0, 0, 0, 0, 0, 0, 0, 0, 0, 0, 0, 0, 0, 0,
            0, 0, 0, 0, 0, 0, 0, 0, 0, 0, 0, 0, 0, 0, 0, 0, 0, 0, 0,
            0, 0, 0, 0, 0, 0, 0, 0, 0, 0, 0, 0, 0, 0, 0, 0, 0, 0, 0,
            0, 0, 0, 0, 1521, 41, 41, 0, 0, 0, 0, 0, 0, 0, 0, 0, 0, 0, 0,
            0, 0, 0, 0, 1280, 0, 0, 0, 0, 0, 0, 0, 0, 0, 0, 0, 0, 0, 0,
            0, 0, 0, 0, 0, 0, 0, 0, 0, 0, 0, 0, 0, 0, 0, 0, 0, 0, 0,
            0, 0, 0, 0, 0, 0, 0, 0, 0, 0, 0, 0, 0, 0, 0, 0, 0, 0, 0,
            0, 0, 0, 0, 0, 0, 0, 0, 0, 0, 0, 0, 0, 0, 0, 0, 0, 0, 0,
            0, 0, 0, 0, 0, 0, 0, 0, 0, 0, 0, 0, 0, 0, 0, 0, 0, 0, 0,
            0, 0, 0, 0, 0, 0, 0, 0, 0, 0, 0, 0, 0, 0, 0, 0, 0, 0, 0,
            0, 0, 0, 0, 0, 0, 0, 0, 0, 0, 0, 0, 0, 0, 0, 0, 0, 0, 0,
            0, 0, 0, 0, 0, 0, 0, 0, 0, 0, 0, 0, 0, 0, 0, 0, 0, 0, 0,
            0, 0, 0, 0, 0, 0, 0, 0, 0, 0, 0, 0, 0, 0, 0, 0, 0, 0, 0,
            0, 0, 0, 0, 0, 0, 0, 0, 0, 0, 0, 0, 0, 0, 0, 0, 0, 0, 0,
            0, 0, 0, 0, 0, 0, 0, 0, 0, 0, 0, 0, 0, 0, 0, 0, 0, 0, 0],
         "height":17,
         "id":8,
         "name":"grass2",
         "opacity":1,
         "type":"tilelayer",
         "visible":true,
         "width":19,
         "x":0,
         "y":0
        }, 
        {
         "data":[159, 159, 159, 159, 159, 159, 159, 159, 159, 159, 159, 159, 159, 159, 159, 159, 159, 159, 159,
            159, 159, 159, 159, 159, 159, 159, 159, 159, 159, 159, 159, 159, 159, 159, 159, 159, 159, 159,
            159, 159, 159, 159, 159, 159, 159, 159, 159, 159, 159, 159, 159, 159, 159, 159, 159, 159, 159,
            159, 159, 159, 159, 159, 159, 159, 159, 159, 159, 159, 159, 159, 159, 159, 159, 159, 159, 159,
            159, 159, 159, 159, 33, 33, 33, 33, 33, 33, 33, 33, 33, 33, 33, 159, 159, 159, 159,
            159, 159, 159, 159, 1320, 1523, 1173, 1129, 1130, 41, 41, 41, 41, 41, 41, 159, 159, 159, 159,
            159, 159, 159, 159, 0, 0, 0, 0, 0, 0, 0, 0, 0, 0, 0, 159, 159, 159, 159,
            159, 159, 159, 159, 0, 0, 0, 0, 0, 0, 0, 0, 0, 0, 0, 159, 159, 159, 159,
            159, 159, 159, 159, 0, 0, 0, 0, 0, 1337, 0, 0, 0, 0, 0, 159, 159, 159, 159,
            159, 159, 159, 159, 0, 1210, 0, 0, 0, 1340, 0, 0, 0, 0, 0, 159, 159, 159, 159,
            159, 159, 159, 159, 0, 1218, 0, 0, 0, 0, 0, 0, 0, 0, 0, 159, 159, 159, 159,
            159, 159, 159, 159, 0, 0, 0, 0, 0, 0, 0, 0, 0, 0, 0, 159, 159, 159, 159,
            159, 159, 159, 159, 0, 0, 0, 0, 0, 0, 0, 0, 0, 0, 0, 159, 159, 159, 159,
            159, 159, 159, 159, 159, 159, 159, 159, 159, 159, 159, 159, 159, 159, 159, 159, 159, 159, 159,
            159, 159, 159, 159, 159, 159, 159, 159, 159, 159, 159, 159, 159, 159, 159, 159, 159, 159, 159,
            159, 159, 159, 159, 159, 159, 159, 159, 159, 159, 159, 159, 159, 159, 159, 159, 159, 159, 159,
            159, 159, 159, 159, 159, 159, 159, 159, 159, 159, 159, 159, 159, 159, 159, 159, 159, 159, 159],
         "height":17,
         "id":3,
         "name":"walls",
         "opacity":1,
         "type":"tilelayer",
         "visible":true,
         "width":19,
         "x":0,
         "y":0
        }, 
        {
         "data":[0, 0, 0, 0, 0, 0, 0, 0, 0, 0, 0, 0, 0, 0, 0, 0, 0, 0, 0,
            0, 0, 0, 0, 0, 0, 0, 0, 0, 0, 0, 0, 0, 0, 0, 0, 0, 0, 0,
            0, 0, 0, 0, 0, 0, 0, 0, 0, 0, 0, 0, 0, 0, 0, 0, 0, 0, 0,
            0, 0, 0, 0, 0, 0, 0, 0, 0, 0, 0, 0, 0, 0, 0, 0, 0, 0, 0,
            0, 0, 0, 0, 1312, 0, 0, 1121, 1122, 0, 0, 0, 0, 1061, 1062, 0, 0, 0, 0,
            0, 0, 0, 0, 0, 0, 0, 0, 0, 0, 0, 879, 0, 1069, 1070, 0, 0, 0, 0,
            0, 0, 0, 0, 0, 0, 0, 0, 0, 0, 0, 0, 0, 0, 0, 0, 0, 0, 0,
            0, 0, 0, 0, 0, 0, 0, 0, 0, 1329, 0, 0, 0, 0, 0, 0, 0, 0, 0,
            0, 0, 0, 0, 1201, 1202, 1203, 0, 0, 0, 0, 0, 0, 0, 0, 0, 0, 0, 0,
            0, 0, 0, 0, 0, 0, 0, 0, 0, 1345, 0, 0, 0, 0, 0, 0, 0, 0, 0,
            0, 0, 0, 0, 0, 0, 0, 0, 0, 0, 0, 0, 0, 0, 0, 0, 0, 0, 0,
            0, 0, 0, 0, 0, 0, 0, 0, 0, 0, 0, 0, 0, 0, 0, 0, 0, 0, 0,
            0, 0, 0, 0, 0, 0, 0, 0, 0, 0, 0, 0, 0, 0, 0, 0, 0, 0, 0,
            0, 0, 0, 0, 0, 0, 0, 0, 0, 0, 0, 0, 0, 0, 0, 0, 0, 0, 0,
            0, 0, 0, 0, 0, 0, 0, 0, 0, 0, 0, 0, 0, 0, 0, 0, 0, 0, 0,
            0, 0, 0, 0, 0, 0, 0, 0, 0, 0, 0, 0, 0, 0, 0, 0, 0, 0, 0,
            0, 0, 0, 0, 0, 0, 0, 0, 0, 0, 0, 0, 0, 0, 0, 0, 0, 0, 0],
         "height":17,
         "id":4,
         "name":"above",
         "opacity":1,
         "type":"tilelayer",
         "visible":true,
         "width":19,
         "x":0,
         "y":0
        }],
 "nextlayerid":9,
 "nextobjectid":3,
 "orientation":"orthogonal",
 "renderorder":"right-down",
 "tiledversion":"1.11.2",
 "tileheight":32,
 "tilesets":[
        {
         "columns":8,
         "firstgid":1,
         "image":"..\/tilesets\/Inside.png",
         "imageheight":8032,
         "imagewidth":256,
         "margin":0,
         "name":"Inside",
         "spacing":0,
         "tilecount":2008,
         "tileheight":32,
         "tilewidth":32
        }],
 "tilewidth":32,
 "type":"map",
 "version":"1.10",
 "width":19
}