{ "compressionlevel":-1,
 "height":40,
 "infinite":false,
 "layers":[
        {
         "draworder":"topdown",
         "id":6,
         "name":"ledge",
         "objects":[
                {
                 "height":13.6363636363636,
                 "id":1,
                 "name":"",
                 "properties":[
                        {
                         "name":"direction",
                         "type":"int",
                         "value":0
                        }],
                 "rotation":0,
                 "type":"",
                 "visible":true,
                 "width":112.121212121212,
                 "x":228.787878787879,
                 "y":968.181818181818
                }, 
                {
                 "height":13.6364,
                 "id":3,
                 "name":"",
                 "properties":[
                        {
                         "name":"direction",
                         "type":"int",
                         "value":0
                        }],
                 "rotation":0,
                 "type":"",
                 "visible":true,
                 "width":66.6664545454546,
                 "x":557.575863636364,
                 "y":971.969678787879
                }, 
                {
                 "height":13.6364,
                 "id":4,
                 "name":"",
                 "properties":[
                        {
                         "name":"direction",
                         "type":"int",
                         "value":0
                        }],
                 "rotation":0,
                 "type":"",
                 "visible":true,
                 "width":587.878575757576,
                 "x":750.000106060606,
                 "y":971.969678787879
                }, 
                {
                 "height":13.6364,
                 "id":5,
                 "name":"",
                 "properties":[
                        {
                         "name":"direction",
                         "type":"int",
                         "value":0
                        }],
                 "rotation":0,
                 "type":"",
                 "visible":true,
                 "width":396.969484848485,
                 "x":936.363742424242,
                 "y":394.696951515151
                }],
         "opacity":1,
         "type":"objectgroup",
         "visible":true,
         "x":0,
         "y":0
        }, 
        {
         "draworder":"topdown",
         "id":5,
         "name":"lights",
         "objects":[
                {
                 "height":122.667,
                 "id":7,
                 "name":"",
                 "properties":[
                        {
                         "name":"intensity",
                         "type":"float",
                         "value":1
                        }, 
                        {
                         "name":"light",
                         "type":"bool",
                         "value":true
                        }, 
                        {
                         "name":"radius",
                         "type":"int",
                         "value":48
                        }],
                 "rotation":0,
                 "type":"",
                 "visible":true,
                 "width":154.667,
                 "x":1077.21195454545,
                 "y":209.878621212121
                }, 
                {
                 "height":78.7276060606061,
                 "id":8,
                 "name":"",
                 "properties":[
                        {
                         "name":"intensity",
                         "type":"float",
                         "value":1
                        }, 
                        {
                         "name":"light",
                         "type":"bool",
                         "value":true
                        }, 
                        {
                         "name":"radius",
                         "type":"int",
                         "value":48
                        }],
                 "rotation":0,
                 "type":"",
                 "visible":true,
                 "width":100.121545454545,
                 "x":780.242257575758,
                 "y":523.514984848485
                }, 
                {
                 "height":101.454878787879,
                 "id":9,
                 "name":"",
                 "properties":[
                        {
                         "name":"intensity",
                         "type":"float",
                         "value":1
                        }, 
                        {
                         "name":"light",
                         "type":"bool",
                         "value":true
                        }, 
                        {
                         "name":"radius",
                         "type":"int",
                         "value":48
                        }],
                 "rotation":0,
                 "type":"",
                 "visible":true,
                 "width":127.394272727273,
                 "x":781.757409090909,
                 "y":747.757409090909
                }, 
                {
                 "height":95.3942727272728,
                 "id":10,
                 "name":"",
                 "properties":[
                        {
                         "name":"intensity",
                         "type":"float",
                         "value":1
                        }, 
                        {
                         "name":"light",
                         "type":"bool",
                         "value":true
                        }, 
                        {
                         "name":"radius",
                         "type":"int",
                         "value":48
                        }],
                 "rotation":0,
                 "type":"",
                 "visible":true,
                 "width":84.9700303030304,
                 "x":1104.48468181818,
                 "y":535.636196969697
                }, 
                {
                 "height":75.697303030303,
                 "id":11,
                 "name":"",
                 "properties":[
                        {
                         "name":"intensity",
                         "type":"float",
                         "value":1
                        }, 
                        {
                         "name":"light",
                         "type":"bool",
                         "value":true
                        }, 
                        {
                         "name":"radius",
                         "type":"int",
                         "value":48
                        }],
                 "rotation":0,
                 "type":"",
                 "visible":true,
                 "width":134.97003030303,
                 "x":780.242257575758,
                 "y":296.242257575758
                }],
         "opacity":1,
         "type":"objectgroup",
         "visible":true,
         "x":0,
         "y":0
        }, 
        {
         "data":[794, 794, 794, 794, 794, 794, 794, 2, 2, 2, 2, 2, 2, 2, 2, 2, 2, 2, 2, 2, 2, 2, 2, 2, 2, 2, 2, 2, 2, 2, 2, 2, 2, 2, 2, 2, 2, 2, 2, 2, 2, 2, 2, 2, 2, 2, 2, 2, 2, 2,
            794, 794, 794, 794, 794, 794, 794, 2, 2, 2, 2, 2, 2, 2, 2, 2, 2, 2, 2, 2, 2, 2, 2, 2, 2, 2, 2, 2, 2, 2, 2, 2, 2, 2, 2, 2, 2, 2, 2, 2, 2, 2, 2, 2, 2, 2, 2, 2, 2, 2,
            794, 794, 794, 794, 794, 794, 794, 2, 2, 2, 2, 2, 2, 2, 2, 2, 2, 2, 2, 2, 266, 267, 268, 2, 2, 2, 2, 2, 2, 2, 2, 2, 2, 2, 2, 2, 2, 2, 2, 2, 2, 2, 2, 2, 2, 2, 2, 2, 2, 2,
            794, 794, 794, 794, 794, 794, 794, 2, 2, 2, 2, 2, 2, 2, 2, 2, 2, 2, 2, 2, 274, 275, 276, 2, 2, 2, 2, 2, 2, 2, 2, 2, 2, 2, 2, 2, 2, 2, 2, 2, 2, 2, 2, 2, 2, 2, 2, 2, 2, 2,
            794, 794, 794, 794, 794, 794, 794, 2, 2, 2, 2, 2, 2, 2, 2, 2, 2, 2, 2, 2, 274, 275, 276, 2, 2, 2, 2, 2, 2, 266, 267, 267, 267, 267, 267, 267, 267, 267, 267, 267, 267, 268, 2, 2, 2, 2, 2, 2, 2, 2,
            794, 794, 794, 794, 794, 794, 794, 2, 2, 2, 2, 2, 2, 2, 2, 2, 2, 2, 2, 2, 274, 275, 276, 2, 2, 2, 2, 2, 2, 274, 275, 275, 275, 275, 275, 275, 275, 275, 275, 275, 275, 276, 2, 2, 2, 2, 2, 2, 2, 2,
            794, 794, 794, 794, 794, 794, 794, 2, 2, 2, 2, 2, 2, 2, 2, 2, 2, 2, 2, 2, 274, 275, 285, 267, 267, 267, 267, 267, 267, 287, 275, 269, 283, 283, 283, 283, 283, 283, 283, 271, 275, 276, 2, 2, 2, 2, 2, 2, 2, 2,
            794, 794, 794, 794, 794, 794, 794, 2, 2, 2, 2, 2, 2, 2, 2, 2, 2, 2, 2, 2, 274, 275, 275, 275, 275, 275, 275, 275, 275, 275, 275, 276, 2, 2, 2, 2, 2, 2, 2, 274, 275, 276, 2, 2, 2, 2, 2, 2, 2, 2,
            794, 794, 794, 794, 794, 794, 794, 2, 2, 2, 2, 2, 2, 2, 2, 2, 2, 2, 2, 2, 274, 275, 269, 283, 283, 283, 283, 283, 283, 283, 283, 284, 2, 2, 2, 2, 2, 2, 2, 274, 275, 276, 2, 2, 2, 2, 2, 2, 2, 2,
            794, 794, 794, 794, 794, 794, 794, 2, 2, 2, 2, 2, 2, 2, 2, 2, 2, 2, 2, 2, 274, 275, 276, 42, 43, 43, 43, 43, 44, 2, 2, 2, 2, 2, 2, 2, 2, 2, 2, 274, 275, 276, 2, 2, 2, 2, 2, 2, 2, 2,
            794, 794, 794, 794, 794, 794, 794, 2, 2, 2, 2, 2, 2, 2, 2, 2, 2, 2, 2, 2, 274, 275, 276, 50, 51, 51, 51, 51, 52, 2, 2, 2, 2, 2, 2, 2, 2, 2, 2, 274, 275, 276, 2, 2, 2, 2, 2, 2, 2, 2,
            794, 794, 794, 794, 794, 794, 794, 2, 2, 2, 2, 2, 2, 2, 2, 2, 2, 2, 2, 2, 274, 275, 276, 50, 51, 51, 51, 51, 52, 2, 2, 2, 2, 2, 2, 2, 2, 2, 2, 282, 283, 284, 2, 2, 2, 2, 2, 2, 2, 2,
            794, 794, 794, 794, 794, 794, 794, 2, 2, 2, 2, 2, 2, 2, 2, 2, 2, 2, 2, 2, 274, 275, 276, 58, 59, 59, 59, 59, 60, 2, 2, 2, 2, 2, 2, 2, 2, 2, 2, 2, 2, 2, 2, 2, 2, 2, 2, 2, 2, 2,
            794, 794, 794, 794, 794, 794, 794, 2, 2, 2, 2, 2, 2, 2, 2, 2, 2, 2, 2, 2, 274, 275, 276, 2, 2, 2, 2, 2, 2, 2, 2, 2, 2, 2, 2, 2, 2, 2, 2, 2, 2, 2, 2, 2, 2, 2, 2, 2, 2, 2,
            794, 794, 794, 794, 794, 2, 2, 2, 2, 2, 2, 2, 2, 2, 2, 2, 2, 2, 2, 2, 274, 275, 276, 2, 2, 2, 2, 2, 2, 2, 2, 2, 2, 2, 2, 2, 2, 2, 2, 2, 2, 2, 2, 2, 2, 2, 2, 2, 2, 2,
            2, 2, 4, 4, 2, 2, 2, 2, 2, 2, 2, 2, 2, 2, 2, 2, 2, 2, 2, 2, 274, 275, 276, 2, 2, 2, 2, 2, 2, 2, 2, 2, 2, 2, 2, 2, 2, 2, 2, 2, 2, 2, 2, 2, 2, 2, 2, 2, 2, 2,
            2, 2, 4, 4, 2, 2, 2, 2, 2, 2, 2, 2, 2, 2, 2, 2, 2, 2, 2, 2, 274, 275, 276, 42, 43, 43, 43, 44, 2, 2, 2, 2, 2, 2, 2, 2, 2, 2, 2, 2, 2, 2, 2, 2, 2, 2, 2, 2, 2, 2,
            155, 155, 155, 155, 155, 155, 155, 155, 156, 2, 2, 2, 2, 266, 267, 267, 267, 267, 267, 267, 287, 275, 276, 50, 51, 51, 51, 52, 2, 266, 267, 268, 2, 2, 2, 2, 2, 2, 2, 266, 267, 268, 2, 2, 2, 2, 2, 2, 2, 2,
            163, 163, 163, 163, 163, 163, 163, 163, 164, 2, 2, 2, 2, 274, 275, 275, 275, 275, 275, 275, 275, 275, 276, 50, 51, 51, 51, 52, 2, 274, 275, 276, 2, 2, 2, 2, 2, 2, 2, 274, 275, 276, 2, 2, 2, 2, 2, 2, 2, 2,
            171, 171, 171, 171, 171, 171, 171, 171, 172, 2, 2, 2, 2, 282, 283, 283, 283, 283, 283, 283, 271, 275, 276, 58, 59, 59, 59, 60, 2, 274, 275, 276, 2, 2, 2, 2, 2, 2, 2, 274, 275, 276, 2, 2, 2, 2, 2, 2, 2, 2,
            2, 2, 4, 4, 2, 2, 2, 2, 2, 2, 2, 2, 2, 2, 2, 2, 2, 2, 2, 2, 274, 275, 285, 267, 267, 267, 267, 267, 267, 287, 275, 285, 267, 267, 267, 267, 286, 267, 267, 287, 275, 276, 2, 2, 2, 2, 2, 2, 2, 2,
            794, 794, 794, 794, 794, 794, 2, 2, 2, 2, 2, 2, 2, 2, 42, 43, 43, 44, 2, 2, 274, 275, 275, 275, 275, 275, 275, 275, 275, 275, 275, 275, 275, 275, 275, 275, 275, 275, 275, 275, 275, 276, 2, 2, 2, 2, 2, 2, 2, 2,
            794, 794, 794, 794, 794, 794, 2, 2, 2, 2, 2, 2, 2, 2, 58, 47, 51, 52, 2, 2, 274, 275, 269, 283, 283, 283, 283, 283, 283, 283, 271, 275, 269, 283, 283, 283, 283, 283, 283, 271, 275, 276, 2, 2, 2, 2, 2, 2, 2, 2,
            794, 794, 794, 794, 794, 794, 2, 2, 2, 2, 2, 2, 2, 2, 2, 50, 51, 61, 44, 2, 274, 275, 276, 2, 2, 2, 2, 2, 2, 2, 274, 275, 276, 2, 2, 2, 2, 2, 2, 274, 275, 276, 2, 2, 2, 2, 2, 2, 2, 2,
            794, 794, 794, 794, 794, 794, 2, 2, 2, 2, 2, 2, 2, 2, 2, 58, 59, 59, 60, 2, 274, 275, 276, 2, 2, 2, 2, 2, 2, 2, 274, 275, 276, 2, 2, 2, 2, 2, 2, 274, 275, 276, 2, 2, 2, 2, 2, 2, 2, 2,
            794, 794, 794, 794, 794, 794, 2, 154, 155, 155, 156, 2, 2, 2, 2, 2, 2, 2, 2, 2, 274, 275, 276, 2, 2, 2, 2, 2, 2, 2, 274, 275, 276, 2, 2, 2, 2, 2, 2, 274, 275, 276, 2, 2, 2, 2, 2, 2, 2, 2,
            794, 794, 794, 794, 794, 794, 2, 162, 163, 163, 164, 2, 2, 2, 2, 2, 2, 2, 2, 2, 274, 275, 276, 2, 2, 2, 2, 2, 2, 2, 274, 275, 276, 2, 2, 2, 2, 2, 2, 274, 275, 276, 2, 2, 2, 2, 2, 2, 2, 2,
            794, 794, 794, 794, 794, 794, 2, 170, 159, 163, 164, 2, 714, 714, 714, 714, 714, 2, 2, 2, 274, 275, 285, 267, 267, 267, 286, 267, 267, 267, 287, 275, 285, 267, 267, 267, 267, 267, 267, 287, 275, 276, 2, 2, 2, 2, 2, 2, 2, 2,
            794, 794, 794, 794, 794, 794, 2, 2, 170, 171, 172, 2, 714, 714, 714, 714, 714, 2, 2, 2, 274, 275, 275, 275, 275, 275, 275, 275, 275, 275, 275, 275, 275, 275, 275, 275, 275, 275, 275, 275, 275, 276, 2, 2, 2, 2, 2, 2, 2, 2,
            794, 794, 794, 794, 794, 794, 2, 2, 2, 2, 2, 2, 714, 714, 714, 714, 714, 2, 2, 2, 282, 283, 283, 283, 283, 283, 283, 283, 283, 283, 283, 283, 283, 283, 283, 283, 283, 283, 283, 283, 283, 284, 2, 2, 2, 2, 2, 2, 2, 2,
            794, 794, 794, 794, 794, 794, 2, 2, 2, 2, 2, 2, 2, 2, 2, 2, 2, 2, 2, 2, 2, 2, 2, 2, 2, 2, 2, 2, 2, 2, 2, 2, 2, 2, 2, 2, 2, 2, 2, 2, 2, 2, 2, 2, 2, 2, 2, 2, 2, 2,
            794, 794, 794, 794, 794, 794, 2, 2, 2, 2, 2, 2, 2, 2, 2, 2, 2, 2, 2, 2, 2, 2, 2, 2, 2, 2, 2, 2, 2, 2, 2, 2, 2, 2, 2, 2, 2, 2, 2, 2, 2, 2, 2, 2, 2, 2, 2, 2, 2, 2,
            794, 794, 794, 794, 794, 794, 2, 2, 2, 2, 2, 2, 2, 2, 154, 155, 155, 155, 155, 155, 155, 155, 155, 155, 155, 155, 155, 155, 155, 155, 155, 155, 155, 155, 155, 155, 155, 155, 155, 156, 2, 2, 2, 2, 2, 2, 2, 2, 2, 2,
            794, 794, 794, 794, 794, 2, 2, 2, 2, 2, 2, 2, 2, 2, 162, 163, 163, 163, 163, 163, 163, 163, 163, 163, 163, 163, 163, 163, 163, 163, 163, 163, 163, 163, 163, 163, 163, 163, 163, 164, 2, 2, 2, 2, 2, 2, 2, 2, 2, 2,
            794, 794, 794, 794, 794, 2, 2, 2, 2, 2, 2, 2, 2, 2, 170, 171, 171, 171, 171, 171, 171, 171, 159, 163, 163, 157, 171, 171, 171, 171, 171, 171, 171, 171, 171, 171, 171, 171, 171, 172, 2, 2, 2, 2, 2, 2, 2, 2, 2, 2,
            794, 794, 794, 794, 794, 2, 2, 2, 2, 2, 2, 2, 2, 2, 2, 2, 2, 2, 2, 2, 2, 2, 162, 163, 163, 164, 2, 2, 2, 2, 2, 2, 2, 2, 2, 2, 2, 2, 2, 2, 2, 2, 2, 2, 2, 2, 2, 2, 2, 2,
            794, 794, 794, 794, 794, 2, 2, 2, 2, 2, 2, 2, 2, 2, 2, 2, 2, 2, 2, 2, 2, 2, 162, 163, 163, 164, 2, 2, 2, 2, 2, 2, 2, 2, 2, 2, 2, 2, 2, 2, 2, 2, 2, 2, 2, 2, 2, 2, 2, 2,
            794, 794, 794, 794, 794, 2, 2, 2, 2, 2, 2, 2, 2, 2, 2, 2, 2, 2, 2, 2, 2, 2, 162, 163, 163, 164, 2, 2, 2, 2, 2, 2, 2, 2, 2, 2, 2, 2, 2, 2, 2, 2, 2, 2, 2, 2, 2, 2, 2, 2,
            794, 794, 794, 794, 794, 2, 2, 2, 2, 2, 2, 2, 2, 2, 2, 2, 2, 2, 2, 2, 2, 2, 162, 163, 163, 164, 2, 2, 2, 2, 2, 2, 2, 2, 2, 2, 2, 2, 2, 2, 2, 2, 2, 2, 2, 2, 2, 2, 2, 2,
            794, 794, 794, 794, 794, 2, 2, 2, 2, 2, 2, 2, 2, 2, 2, 2, 2, 2, 2, 2, 2, 2, 162, 163, 163, 164, 2, 2, 2, 2, 2, 2, 2, 2, 2, 2, 2, 2, 2, 2, 2, 2, 2, 2, 2, 2, 2, 2, 2, 2],
         "height":40,
         "id":2,
         "name":"floor",
         "opacity":1,
         "type":"tilelayer",
         "visible":true,
         "width":50,
         "x":0,
         "y":0
        }, 
        {
         "data":[0, 0, 0, 0, 0, 0, 0, 0, 0, 0, 0, 0, 0, 0, 0, 0, 0, 0, 0, 0, 0, 0, 0, 0, 0, 0, 0, 0, 0, 0, 0, 0, 0, 0, 0, 0, 0, 0, 0, 0, 0, 0, 0, 0, 0, 0, 0, 0, 0, 0,
            0, 0, 0, 0, 0, 0, 0, 0, 0, 0, 0, 0, 0, 0, 0, 0, 0, 0, 0, 0, 0, 0, 0, 0, 0, 0, 0, 0, 0, 0, 0, 0, 0, 0, 0, 0, 0, 0, 0, 0, 0, 0, 0, 0, 0, 0, 0, 0, 0, 0,
            0, 0, 0, 0, 0, 0, 0, 0, 0, 0, 0, 0, 0, 0, 0, 0, 0, 0, 0, 0, 0, 0, 0, 0, 0, 0, 0, 0, 0, 0, 0, 0, 0, 0, 0, 0, 0, 0, 0, 0, 0, 0, 0, 0, 0, 0, 0, 0, 0, 0,
            0, 0, 0, 0, 0, 0, 0, 0, 0, 0, 0, 0, 0, 0, 0, 0, 0, 0, 0, 0, 0, 0, 0, 0, 0, 0, 0, 0, 0, 0, 0, 0, 0, 0, 0, 0, 0, 0, 0, 0, 0, 0, 0, 0, 0, 0, 0, 0, 0, 0,
            0, 0, 0, 0, 0, 0, 0, 0, 0, 0, 0, 0, 0, 0, 0, 0, 0, 0, 0, 0, 0, 0, 0, 0, 0, 0, 0, 0, 0, 0, 0, 0, 0, 0, 0, 0, 0, 0, 0, 0, 0, 0, 0, 0, 0, 0, 0, 0, 0, 0,
            0, 0, 0, 0, 0, 0, 0, 0, 0, 0, 0, 0, 0, 0, 0, 0, 0, 0, 0, 0, 0, 0, 0, 0, 0, 0, 0, 0, 0, 0, 0, 0, 0, 0, 0, 0, 0, 0, 0, 0, 0, 0, 0, 0, 0, 0, 0, 0, 0, 0,
            0, 0, 0, 0, 0, 0, 0, 0, 0, 0, 0, 0, 0, 0, 0, 0, 0, 0, 0, 0, 0, 0, 0, 0, 0, 0, 0, 0, 0, 0, 0, 0, 0, 0, 0, 0, 0, 0, 0, 0, 0, 0, 0, 0, 0, 0, 0, 0, 0, 0,
            0, 0, 0, 0, 0, 0, 0, 0, 0, 0, 0, 0, 0, 0, 0, 0, 0, 0, 0, 0, 0, 0, 0, 0, 0, 0, 0, 0, 0, 0, 0, 0, 0, 0, 0, 0, 0, 0, 0, 0, 0, 0, 0, 0, 0, 0, 0, 0, 0, 0,
            0, 0, 0, 0, 0, 0, 0, 0, 0, 0, 0, 0, 0, 0, 0, 0, 0, 0, 0, 0, 0, 0, 0, 0, 0, 0, 0, 0, 0, 0, 0, 0, 0, 0, 0, 0, 0, 0, 0, 0, 0, 0, 0, 0, 0, 0, 0, 0, 0, 0,
            0, 0, 0, 0, 0, 0, 0, 0, 0, 0, 0, 0, 0, 0, 0, 0, 0, 0, 0, 0, 0, 0, 0, 0, 0, 0, 0, 0, 0, 0, 0, 0, 0, 0, 0, 0, 0, 0, 0, 0, 0, 0, 0, 0, 0, 0, 0, 0, 0, 0,
            0, 0, 0, 0, 0, 0, 0, 0, 0, 0, 0, 0, 0, 0, 0, 0, 0, 0, 0, 0, 0, 0, 0, 0, 0, 0, 0, 0, 0, 0, 0, 0, 0, 0, 0, 0, 0, 0, 0, 0, 0, 0, 0, 0, 0, 0, 0, 0, 0, 0,
            0, 0, 0, 0, 0, 0, 0, 0, 0, 0, 0, 0, 0, 0, 0, 0, 0, 0, 0, 0, 0, 0, 0, 0, 0, 0, 0, 0, 0, 0, 0, 0, 0, 0, 0, 0, 0, 0, 0, 0, 0, 0, 0, 0, 0, 0, 0, 0, 0, 0,
            0, 0, 0, 0, 0, 0, 0, 0, 0, 0, 0, 0, 0, 0, 0, 0, 0, 0, 0, 0, 0, 0, 0, 0, 0, 0, 0, 0, 0, 811, 829, 829, 829, 829, 829, 829, 829, 829, 829, 829, 829, 815, 0, 0, 0, 0, 0, 0, 0, 0,
            0, 0, 0, 0, 0, 0, 0, 0, 0, 0, 0, 0, 0, 0, 0, 0, 0, 0, 0, 0, 0, 0, 0, 0, 0, 0, 0, 0, 0, 0, 0, 0, 0, 0, 0, 0, 0, 0, 0, 957, 0, 957, 0, 0, 0, 0, 0, 0, 0, 0,
            0, 0, 0, 0, 0, 0, 0, 0, 0, 0, 0, 0, 0, 0, 0, 0, 0, 0, 0, 0, 0, 0, 0, 0, 0, 0, 0, 0, 0, 0, 0, 0, 0, 0, 0, 0, 0, 0, 957, 0, 957, 0, 0, 0, 0, 0, 0, 0, 0, 0,
            0, 0, 0, 0, 0, 0, 0, 0, 0, 0, 0, 0, 0, 0, 0, 0, 0, 0, 0, 0, 0, 0, 0, 0, 0, 0, 0, 0, 0, 0, 0, 0, 0, 0, 0, 0, 0, 0, 0, 0, 0, 0, 0, 0, 0, 0, 0, 0, 0, 0,
            0, 0, 0, 0, 0, 0, 0, 0, 0, 0, 0, 0, 0, 0, 0, 0, 0, 0, 0, 0, 0, 0, 0, 0, 0, 0, 0, 0, 0, 0, 0, 0, 0, 0, 0, 0, 0, 0, 0, 0, 0, 0, 0, 0, 0, 0, 0, 0, 0, 0,
            0, 0, 0, 0, 0, 0, 0, 0, 0, 0, 0, 0, 0, 0, 0, 0, 0, 0, 0, 0, 0, 0, 0, 0, 0, 0, 0, 0, 0, 0, 0, 0, 0, 0, 0, 0, 0, 0, 0, 0, 0, 0, 0, 0, 0, 0, 0, 0, 0, 0,
            0, 0, 0, 0, 0, 0, 0, 0, 0, 0, 0, 0, 0, 0, 0, 0, 0, 0, 0, 0, 0, 0, 0, 0, 0, 0, 0, 0, 0, 0, 0, 0, 0, 0, 0, 0, 0, 0, 0, 0, 0, 0, 0, 0, 0, 0, 0, 0, 0, 0,
            0, 0, 0, 0, 0, 0, 0, 0, 0, 0, 0, 0, 0, 0, 0, 0, 0, 0, 0, 0, 0, 0, 0, 0, 0, 0, 0, 0, 0, 0, 0, 0, 0, 0, 0, 0, 0, 0, 0, 0, 0, 0, 0, 0, 0, 0, 0, 0, 0, 0,
            0, 0, 0, 0, 0, 0, 0, 0, 0, 0, 0, 0, 0, 0, 0, 0, 0, 0, 0, 0, 0, 0, 0, 0, 0, 0, 0, 0, 0, 0, 0, 0, 0, 0, 0, 0, 0, 0, 0, 0, 0, 0, 0, 0, 0, 0, 0, 0, 0, 0,
            0, 0, 0, 0, 0, 0, 0, 0, 0, 0, 0, 0, 0, 0, 0, 0, 0, 0, 0, 0, 0, 0, 0, 0, 0, 0, 0, 0, 0, 0, 0, 0, 0, 0, 0, 0, 0, 0, 0, 0, 0, 0, 0, 0, 0, 0, 0, 0, 0, 0,
            0, 0, 0, 0, 0, 0, 0, 0, 0, 0, 0, 0, 0, 0, 0, 0, 0, 0, 0, 0, 0, 0, 0, 0, 0, 0, 0, 0, 0, 0, 0, 0, 0, 0, 0, 0, 0, 0, 0, 0, 0, 0, 0, 0, 0, 0, 0, 0, 0, 0,
            0, 0, 0, 0, 0, 0, 0, 0, 0, 0, 0, 0, 0, 0, 0, 0, 0, 0, 0, 0, 0, 0, 0, 0, 0, 0, 0, 0, 0, 0, 0, 0, 0, 0, 957, 0, 957, 0, 0, 0, 0, 0, 0, 0, 0, 0, 0, 0, 0, 0,
            0, 0, 0, 0, 0, 0, 0, 0, 0, 0, 0, 0, 0, 0, 0, 0, 0, 0, 0, 0, 0, 0, 0, 0, 0, 0, 0, 0, 0, 0, 0, 0, 0, 0, 0, 957, 0, 957, 0, 0, 0, 0, 0, 0, 0, 0, 0, 0, 0, 0,
            0, 0, 0, 0, 0, 0, 0, 0, 0, 0, 0, 0, 0, 0, 0, 0, 0, 0, 0, 0, 0, 0, 0, 0, 0, 0, 0, 0, 0, 0, 0, 0, 0, 0, 957, 0, 957, 0, 0, 0, 0, 0, 0, 0, 0, 0, 0, 0, 0, 0,
            0, 0, 0, 0, 0, 0, 0, 0, 0, 0, 0, 0, 0, 0, 0, 0, 0, 0, 0, 0, 0, 0, 0, 0, 0, 0, 0, 0, 0, 0, 0, 0, 0, 0, 0, 957, 0, 957, 0, 0, 0, 0, 0, 0, 0, 0, 0, 0, 0, 0,
            0, 0, 0, 0, 0, 0, 0, 0, 0, 0, 0, 0, 0, 0, 0, 0, 0, 0, 0, 0, 0, 0, 0, 0, 0, 0, 0, 0, 0, 0, 0, 0, 0, 0, 0, 0, 0, 0, 0, 0, 0, 0, 0, 0, 0, 0, 0, 0, 0, 0,
            0, 0, 0, 0, 0, 0, 0, 0, 0, 0, 0, 0, 0, 0, 0, 0, 0, 0, 0, 0, 0, 0, 0, 0, 0, 0, 0, 0, 0, 0, 0, 0, 0, 0, 0, 0, 0, 0, 0, 0, 0, 0, 0, 0, 0, 0, 0, 0, 0, 0,
            0, 0, 0, 0, 0, 0, 0, 0, 0, 0, 0, 0, 0, 0, 0, 0, 0, 0, 0, 0, 0, 0, 0, 0, 0, 0, 0, 0, 0, 0, 0, 0, 0, 0, 0, 0, 0, 0, 0, 0, 0, 0, 0, 0, 0, 0, 0, 0, 0, 0,
            0, 0, 0, 0, 0, 0, 0, 829, 829, 829, 815, 0, 0, 0, 0, 0, 0, 811, 829, 815, 0, 0, 0, 811, 829, 829, 829, 829, 829, 829, 829, 829, 829, 829, 829, 829, 829, 829, 829, 829, 829, 815, 0, 0, 0, 0, 0, 0, 0, 0,
            0, 0, 0, 0, 0, 0, 0, 0, 0, 0, 0, 858, 858, 858, 858, 858, 858, 0, 0, 0, 0, 0, 0, 0, 0, 0, 0, 0, 957, 0, 957, 0, 957, 0, 0, 0, 957, 0, 957, 0, 957, 0, 0, 0, 0, 0, 0, 0, 0, 0,
            0, 0, 0, 0, 0, 0, 0, 0, 0, 0, 0, 0, 0, 0, 0, 0, 0, 0, 0, 0, 0, 0, 0, 0, 0, 0, 0, 0, 0, 0, 0, 0, 0, 0, 0, 0, 0, 0, 0, 0, 0, 0, 0, 0, 0, 0, 0, 0, 0, 0,
            0, 0, 0, 0, 0, 0, 0, 0, 0, 0, 0, 0, 0, 0, 0, 0, 0, 0, 0, 0, 0, 0, 0, 0, 0, 0, 0, 0, 0, 0, 0, 0, 0, 0, 0, 0, 0, 0, 0, 0, 0, 0, 0, 0, 0, 0, 0, 0, 0, 0,
            0, 0, 0, 0, 0, 0, 0, 0, 0, 0, 0, 0, 0, 0, 0, 0, 0, 0, 0, 0, 0, 0, 0, 0, 0, 0, 0, 0, 0, 0, 0, 0, 0, 0, 0, 0, 0, 0, 0, 0, 0, 0, 0, 0, 0, 0, 0, 0, 0, 0,
            0, 0, 0, 0, 0, 0, 0, 0, 0, 0, 0, 0, 0, 0, 0, 0, 0, 0, 0, 0, 0, 0, 0, 0, 0, 0, 0, 0, 0, 0, 0, 0, 0, 0, 0, 0, 0, 0, 0, 0, 0, 0, 0, 0, 0, 0, 0, 0, 0, 0,
            0, 0, 0, 0, 0, 0, 0, 0, 0, 0, 0, 0, 0, 0, 0, 0, 0, 0, 0, 0, 0, 0, 0, 0, 0, 0, 0, 0, 0, 0, 0, 0, 0, 0, 0, 0, 0, 0, 0, 0, 0, 0, 0, 0, 0, 0, 0, 0, 0, 0,
            0, 0, 0, 0, 0, 0, 0, 0, 0, 0, 0, 0, 0, 0, 0, 0, 0, 0, 0, 0, 0, 0, 0, 0, 0, 0, 0, 0, 0, 0, 0, 0, 0, 0, 0, 0, 0, 0, 0, 0, 0, 0, 0, 0, 0, 0, 0, 0, 0, 0,
            0, 0, 0, 0, 0, 0, 0, 0, 0, 0, 0, 0, 0, 0, 0, 0, 0, 0, 0, 0, 0, 0, 0, 0, 0, 0, 0, 0, 0, 0, 0, 0, 0, 0, 0, 0, 0, 0, 0, 0, 0, 0, 0, 0, 0, 0, 0, 0, 0, 0,
            0, 0, 0, 0, 0, 0, 0, 0, 0, 0, 0, 0, 0, 0, 0, 0, 0, 0, 0, 0, 0, 0, 0, 0, 0, 0, 0, 0, 0, 0, 0, 0, 0, 0, 0, 0, 0, 0, 0, 0, 0, 0, 0, 0, 0, 0, 0, 0, 0, 0],
         "height":40,
         "id":1,
         "name":"grass",
         "opacity":1,
         "type":"tilelayer",
         "visible":true,
         "width":50,
         "x":0,
         "y":0
        }, 
        {
         "data":[786, 786, 786, 786, 787, 0, 0, 795, 427, 428, 427, 428, 427, 428, 427, 428, 427, 428, 1281, 0, 0, 0, 0, 0, 419, 420, 419, 420, 427, 428, 427, 428, 427, 428, 427, 428, 427, 428, 427, 428, 427, 428, 427, 428, 427, 428, 427, 428, 427, 428,
            0, 0, 0, 0, 817, 787, 0, 795, 419, 420, 419, 420, 419, 420, 419, 420, 419, 420, 1281, 0, 0, 0, 0, 954, 427, 428, 427, 428, 419, 420, 419, 420, 419, 420, 419, 420, 419, 420, 419, 420, 419, 420, 419, 420, 419, 420, 419, 420, 419, 420,
            785, 786, 786, 787, 0, 795, 0, 795, 427, 428, 427, 428, 427, 428, 427, 428, 427, 428, 1281, 0, 0, 0, 0, 0, 419, 420, 419, 420, 427, 428, 427, 428, 427, 428, 427, 428, 427, 428, 427, 428, 427, 428, 427, 428, 427, 428, 427, 428, 427, 428,
            793, 0, 0, 817, 787, 817, 787, 795, 435, 436, 435, 436, 435, 436, 435, 436, 435, 436, 1281, 0, 0, 0, 0, 0, 427, 428, 427, 428, 435, 436, 435, 436, 435, 436, 435, 436, 435, 436, 435, 436, 435, 436, 419, 420, 419, 420, 419, 420, 419, 420,
            793, 0, 0, 0, 795, 0, 795, 795, 1298, 1298, 1298, 1298, 1298, 1298, 1298, 1298, 1298, 1298, 1322, 0, 0, 0, 0, 0, 435, 436, 435, 436, 0, 0, 0, 0, 0, 0, 0, 0, 0, 0, 0, 0, 0, 0, 427, 428, 427, 428, 427, 428, 427, 428,
            793, 0, 0, 0, 795, 0, 795, 795, 0, 0, 0, 0, 0, 0, 0, 0, 0, 0, 948, 0, 0, 0, 0, 0, 0, 0, 0, 0, 0, 0, 0, 0, 0, 0, 0, 0, 0, 0, 0, 0, 0, 0, 419, 420, 419, 420, 419, 420, 419, 420,
            793, 0, 0, 0, 795, 0, 795, 795, 0, 1279, 427, 428, 427, 428, 427, 428, 427, 428, 1280, 0, 0, 0, 0, 0, 0, 0, 0, 0, 0, 0, 0, 0, 0, 0, 0, 0, 0, 0, 0, 0, 0, 0, 427, 428, 427, 428, 427, 428, 427, 428,
            793, 0, 0, 0, 795, 0, 795, 795, 0, 1282, 419, 420, 419, 420, 419, 420, 419, 420, 1281, 476, 0, 0, 0, 0, 0, 0, 0, 0, 0, 0, 0, 0, 0, 2809, 2810, 2811, 2812, 2813, 2815, 0, 0, 0, 419, 420, 419, 420, 419, 420, 419, 420,
            793, 0, 0, 0, 795, 0, 795, 795, 0, 1282, 427, 428, 427, 428, 427, 428, 427, 428, 1281, 0, 0, 0, 0, 0, 0, 0, 0, 0, 0, 0, 0, 0, 0, 2817, 2818, 2819, 2820, 2821, 2823, 0, 0, 0, 427, 428, 427, 428, 427, 428, 427, 428,
            793, 0, 0, 809, 803, 0, 795, 795, 0, 1282, 419, 420, 419, 420, 419, 420, 419, 420, 1281, 476, 0, 0, 0, 476, 2009, 2010, 2010, 2010, 2011, 0, 0, 0, 0, 2825, 2826, 2827, 2828, 2829, 2831, 0, 0, 0, 419, 420, 419, 420, 419, 420, 419, 420,
            793, 0, 0, 795, 0, 0, 795, 795, 0, 1282, 427, 428, 427, 428, 427, 428, 427, 428, 1281, 0, 0, 0, 0, 0, 0, 0, 1892, 1892, 1892, 0, 0, 0, 972, 2833, 2834, 2835, 2836, 2837, 2839, 0, 0, 0, 427, 428, 427, 428, 427, 428, 427, 428,
            801, 802, 802, 803, 0, 809, 803, 795, 0, 1282, 419, 420, 419, 420, 419, 420, 419, 420, 1281, 476, 0, 0, 0, 476, 2012, 2013, 2014, 2015, 2016, 0, 0, 0, 0, 0, 0, 0, 0, 0, 0, 0, 0, 0, 419, 420, 419, 420, 419, 420, 419, 420,
            0, 0, 0, 0, 809, 803, 0, 795, 0, 1282, 427, 428, 427, 428, 427, 428, 427, 428, 1281, 0, 0, 0, 0, 0, 0, 0, 0, 476, 476, 0, 0, 0, 0, 0, 0, 0, 0, 0, 0, 0, 0, 0, 427, 428, 427, 428, 427, 428, 427, 428,
            802, 802, 802, 802, 803, 0, 0, 795, 0, 1282, 419, 420, 419, 420, 419, 420, 419, 420, 1281, 476, 0, 0, 0, 0, 0, 0, 0, 0, 0, 0, 0, 0, 0, 0, 0, 0, 0, 0, 0, 0, 0, 0, 419, 420, 419, 420, 419, 420, 419, 420,
            0, 0, 0, 0, 0, 809, 802, 803, 0, 1282, 427, 428, 427, 428, 427, 428, 427, 428, 1281, 0, 0, 0, 0, 0, 0, 0, 0, 0, 0, 0, 0, 0, 0, 0, 0, 0, 0, 0, 0, 0, 0, 0, 427, 428, 427, 428, 427, 428, 427, 428,
            802, 802, 802, 802, 802, 803, 0, 0, 0, 1282, 435, 436, 435, 436, 435, 436, 435, 436, 1281, 476, 0, 0, 0, 0, 0, 0, 0, 0, 1298, 1298, 1298, 1298, 1298, 1298, 1298, 1298, 1298, 1298, 1298, 1298, 1298, 1298, 419, 420, 419, 420, 419, 420, 419, 420,
            0, 0, 0, 0, 0, 0, 0, 0, 0, 1295, 1298, 1298, 1298, 1298, 1298, 1298, 1298, 1298, 1296, 0, 953, 0, 0, 476, 2009, 2010, 2010, 2011, 0, 0, 0, 0, 0, 0, 0, 0, 0, 0, 0, 0, 0, 0, 427, 428, 427, 428, 427, 428, 427, 428,
            0, 0, 0, 0, 0, 0, 0, 0, 0, 0, 0, 0, 0, 0, 0, 0, 0, 0, 0, 0, 0, 0, 0, 0, 0, 1892, 1892, 1892, 0, 0, 0, 0, 0, 0, 2657, 2658, 2659, 2660, 0, 0, 0, 0, 419, 420, 419, 420, 419, 420, 419, 420,
            0, 0, 0, 0, 0, 0, 0, 0, 0, 0, 0, 0, 0, 0, 0, 0, 0, 0, 0, 0, 0, 0, 0, 476, 2013, 2014, 2015, 2016, 0, 0, 0, 0, 0, 0, 2665, 2666, 2667, 2668, 0, 0, 0, 0, 427, 428, 427, 428, 427, 428, 427, 428,
            0, 0, 0, 0, 0, 0, 0, 0, 0, 0, 0, 0, 0, 0, 0, 0, 0, 0, 0, 0, 0, 0, 0, 0, 0, 0, 0, 0, 0, 0, 0, 0, 0, 0, 2673, 2674, 2675, 2676, 0, 0, 0, 0, 419, 420, 419, 420, 419, 420, 419, 420,
            786, 786, 786, 786, 786, 786, 787, 0, 0, 0, 0, 0, 0, 0, 0, 0, 0, 0, 0, 0, 0, 0, 0, 0, 0, 0, 0, 0, 0, 0, 0, 0, 0, 0, 0, 0, 0, 0, 0, 0, 0, 0, 427, 428, 427, 428, 427, 428, 427, 428,
            0, 785, 789, 789, 787, 0, 795, 0, 0, 0, 0, 0, 0, 0, 0, 0, 0, 0, 0, 0, 0, 0, 0, 0, 0, 0, 0, 0, 0, 0, 0, 0, 0, 0, 0, 0, 0, 0, 0, 0, 0, 0, 419, 420, 419, 420, 419, 420, 419, 420,
            785, 818, 0, 0, 795, 0, 795, 0, 0, 0, 0, 0, 0, 0, 0, 0, 0, 0, 0, 0, 0, 0, 0, 0, 0, 0, 0, 0, 0, 0, 0, 0, 0, 0, 0, 0, 0, 0, 0, 0, 0, 0, 427, 428, 427, 428, 427, 428, 427, 428,
            793, 0, 0, 0, 817, 787, 795, 425, 426, 427, 428, 0, 0, 0, 0, 0, 0, 0, 0, 0, 0, 0, 0, 0, 2617, 2618, 2619, 2620, 2621, 0, 0, 0, 0, 0, 0, 0, 0, 0, 0, 0, 0, 0, 419, 420, 419, 420, 419, 420, 419, 420,
            793, 0, 0, 0, 0, 795, 795, 433, 434, 435, 436, 948, 427, 428, 0, 0, 0, 0, 0, 0, 0, 0, 0, 0, 2625, 2626, 2627, 2628, 2629, 0, 0, 0, 0, 0, 0, 0, 0, 0, 0, 0, 0, 0, 427, 428, 427, 428, 427, 428, 427, 428,
            793, 0, 0, 0, 0, 795, 795, 0, 0, 0, 0, 0, 435, 436, 0, 0, 0, 0, 0, 0, 0, 0, 0, 0, 2633, 2634, 2635, 2636, 2637, 0, 0, 0, 0, 0, 0, 0, 0, 0, 0, 0, 0, 0, 419, 420, 419, 420, 419, 420, 419, 420,
            793, 0, 0, 0, 0, 795, 795, 0, 0, 0, 0, 705, 706, 706, 706, 706, 707, 0, 0, 0, 0, 0, 0, 0, 2641, 2642, 2643, 2644, 2645, 0, 0, 0, 0, 0, 0, 0, 0, 0, 0, 0, 0, 0, 427, 428, 427, 428, 427, 428, 427, 428,
            793, 0, 0, 0, 0, 795, 795, 0, 0, 0, 0, 713, 0, 0, 0, 0, 715, 0, 0, 0, 0, 0, 0, 0, 0, 0, 0, 0, 0, 0, 0, 0, 0, 0, 0, 0, 0, 0, 0, 0, 0, 0, 419, 420, 419, 420, 419, 420, 419, 420,
            818, 0, 0, 0, 0, 795, 795, 0, 0, 0, 0, 713, 0, 0, 0, 0, 715, 0, 0, 0, 0, 0, 0, 0, 0, 0, 0, 0, 0, 0, 0, 0, 0, 0, 0, 0, 0, 0, 0, 0, 0, 0, 427, 428, 427, 428, 427, 428, 427, 428,
            0, 0, 0, 0, 0, 795, 795, 0, 0, 0, 0, 713, 0, 0, 0, 0, 715, 0, 0, 0, 0, 0, 0, 0, 0, 0, 0, 0, 0, 0, 0, 0, 0, 0, 0, 0, 0, 0, 0, 0, 0, 0, 419, 420, 419, 420, 419, 420, 419, 420,
            0, 0, 0, 0, 0, 795, 795, 0, 0, 0, 0, 713, 714, 714, 714, 714, 715, 0, 0, 0, 0, 0, 0, 0, 0, 0, 0, 0, 0, 0, 0, 0, 0, 0, 0, 0, 0, 0, 0, 0, 0, 0, 427, 428, 427, 428, 427, 428, 427, 428,
            0, 0, 0, 0, 809, 803, 795, 0, 0, 0, 0, 0, 0, 0, 0, 0, 0, 0, 0, 0, 954, 0, 0, 0, 0, 0, 0, 0, 0, 0, 0, 0, 0, 0, 0, 0, 0, 0, 0, 0, 0, 0, 419, 420, 419, 420, 419, 420, 419, 420,
            0, 0, 0, 0, 795, 0, 795, 0, 0, 0, 0, 0, 0, 0, 0, 0, 0, 0, 0, 0, 0, 0, 0, 0, 0, 0, 0, 0, 0, 0, 0, 0, 0, 0, 0, 0, 0, 0, 0, 0, 0, 0, 427, 428, 427, 428, 427, 428, 427, 428,
            0, 0, 0, 0, 795, 809, 803, 0, 0, 0, 0, 0, 0, 0, 0, 0, 0, 0, 0, 0, 0, 0, 0, 0, 0, 0, 0, 0, 0, 0, 0, 0, 0, 0, 0, 0, 0, 0, 0, 0, 0, 0, 419, 420, 419, 420, 419, 420, 419, 420,
            0, 0, 0, 0, 795, 795, 427, 428, 427, 428, 427, 428, 427, 428, 0, 0, 0, 0, 0, 0, 0, 0, 0, 0, 0, 0, 0, 0, 0, 0, 0, 0, 0, 0, 0, 0, 0, 0, 0, 0, 0, 0, 427, 428, 427, 428, 427, 428, 427, 428,
            0, 0, 0, 0, 795, 795, 419, 420, 419, 420, 419, 420, 419, 420, 0, 0, 0, 0, 0, 0, 0, 0, 0, 0, 0, 0, 0, 0, 0, 0, 0, 0, 0, 0, 0, 0, 0, 0, 0, 0, 0, 0, 419, 420, 419, 420, 419, 420, 419, 420,
            0, 0, 0, 0, 795, 795, 427, 428, 427, 428, 427, 428, 427, 428, 427, 428, 427, 428, 427, 428, 427, 428, 0, 0, 0, 0, 427, 428, 427, 428, 427, 428, 427, 428, 427, 428, 427, 428, 427, 428, 427, 428, 427, 428, 427, 428, 427, 428, 427, 428,
            0, 0, 0, 0, 795, 795, 419, 420, 419, 420, 419, 420, 419, 420, 419, 420, 419, 420, 419, 420, 419, 420, 0, 0, 0, 0, 419, 420, 419, 420, 419, 420, 419, 420, 419, 420, 419, 420, 419, 420, 419, 420, 419, 420, 419, 420, 419, 420, 419, 420,
            0, 0, 0, 0, 795, 795, 427, 428, 427, 428, 427, 428, 427, 428, 427, 428, 427, 428, 427, 428, 427, 428, 0, 0, 0, 0, 427, 428, 427, 428, 427, 428, 427, 428, 427, 428, 427, 428, 427, 428, 427, 428, 427, 428, 427, 428, 427, 428, 427, 428,
            0, 0, 0, 0, 795, 795, 419, 420, 419, 420, 419, 420, 419, 420, 419, 420, 419, 420, 419, 420, 419, 420, 0, 0, 0, 0, 419, 420, 419, 420, 419, 420, 419, 420, 419, 420, 419, 420, 419, 420, 419, 420, 419, 420, 419, 420, 419, 420, 419, 420],
         "height":40,
         "id":3,
         "name":"walls",
         "opacity":1,
         "type":"tilelayer",
         "visible":true,
         "width":50,
         "x":0,
         "y":0
        }, 
        {
         "data":[0, 0, 0, 0, 0, 0, 0, 0, 0, 0, 0, 0, 0, 0, 0, 0, 0, 0, 0, 0, 0, 0, 0, 0, 0, 0, 0, 0, 0, 0, 0, 0, 0, 0, 0, 0, 0, 0, 0, 0, 0, 0, 0, 0, 0, 0, 0, 0, 0, 0,
            0, 0, 0, 0, 0, 0, 0, 0, 0, 0, 0, 0, 0, 0, 0, 0, 0, 0, 0, 0, 0, 0, 0, 0, 0, 0, 0, 0, 0, 0, 0, 0, 0, 0, 0, 0, 0, 0, 0, 0, 0, 0, 0, 0, 0, 0, 0, 0, 0, 0,
            0, 0, 0, 0, 0, 0, 0, 0, 0, 0, 0, 0, 0, 0, 0, 0, 0, 0, 0, 0, 0, 0, 0, 0, 0, 0, 0, 0, 0, 0, 0, 0, 0, 0, 0, 0, 0, 0, 0, 0, 0, 0, 0, 0, 0, 0, 0, 0, 0, 0,
            0, 0, 0, 0, 0, 0, 0, 0, 0, 0, 0, 0, 0, 0, 0, 0, 0, 0, 0, 0, 0, 0, 0, 0, 0, 0, 0, 0, 0, 0, 0, 0, 0, 0, 0, 0, 0, 0, 0, 0, 0, 0, 0, 0, 0, 0, 0, 0, 0, 0,
            0, 0, 0, 0, 0, 0, 0, 0, 0, 0, 0, 0, 0, 0, 0, 0, 0, 0, 0, 0, 0, 0, 0, 0, 0, 0, 0, 0, 0, 0, 0, 0, 0, 0, 0, 0, 0, 0, 0, 0, 0, 0, 0, 0, 0, 0, 0, 0, 0, 0,
            0, 0, 0, 0, 0, 0, 0, 0, 0, 0, 421, 422, 421, 422, 421, 422, 421, 422, 0, 0, 0, 0, 0, 0, 0, 0, 0, 0, 0, 0, 0, 0, 0, 0, 0, 0, 0, 0, 0, 0, 0, 0, 0, 0, 0, 0, 0, 0, 0, 0,
            0, 0, 0, 0, 0, 0, 0, 0, 0, 0, 0, 0, 0, 0, 0, 0, 0, 0, 0, 0, 0, 0, 0, 0, 0, 0, 0, 0, 0, 0, 0, 0, 0, 2801, 2803, 2804, 2805, 2806, 2807, 0, 0, 0, 0, 0, 0, 0, 0, 0, 0, 0,
            0, 0, 0, 0, 0, 0, 0, 0, 0, 0, 0, 0, 0, 0, 0, 0, 0, 0, 0, 0, 0, 0, 0, 0, 0, 0, 0, 0, 0, 0, 0, 0, 0, 0, 0, 0, 0, 0, 0, 0, 0, 0, 0, 0, 0, 0, 0, 0, 0, 0,
            0, 0, 0, 0, 0, 0, 0, 0, 0, 0, 0, 0, 0, 0, 0, 0, 0, 0, 0, 0, 0, 0, 0, 0, 2001, 2002, 2002, 2042, 2003, 0, 0, 0, 0, 0, 0, 0, 0, 0, 0, 0, 0, 0, 0, 0, 0, 0, 0, 0, 0, 0,
            0, 0, 0, 0, 0, 0, 0, 0, 0, 0, 0, 0, 0, 0, 0, 0, 0, 0, 0, 0, 0, 0, 0, 0, 0, 0, 2049, 2050, 2051, 0, 0, 0, 964, 0, 0, 0, 0, 0, 0, 0, 0, 0, 0, 0, 0, 0, 0, 0, 0, 0,
            0, 0, 0, 0, 0, 0, 0, 0, 0, 0, 0, 0, 0, 0, 0, 0, 0, 0, 0, 0, 0, 0, 0, 0, 2089, 2090, 2057, 2058, 2059, 0, 0, 0, 0, 0, 0, 0, 0, 0, 0, 0, 0, 0, 0, 0, 0, 0, 0, 0, 0, 0,
            0, 0, 0, 0, 0, 0, 0, 0, 0, 0, 0, 0, 0, 0, 0, 0, 0, 0, 0, 0, 0, 0, 0, 0, 0, 0, 0, 0, 0, 0, 0, 0, 0, 0, 0, 0, 0, 0, 0, 0, 0, 0, 0, 0, 0, 0, 0, 0, 0, 0,
            0, 0, 0, 0, 0, 0, 0, 0, 0, 0, 0, 0, 0, 0, 0, 0, 0, 0, 0, 0, 0, 0, 0, 0, 0, 0, 0, 0, 0, 0, 0, 0, 0, 0, 0, 0, 0, 0, 0, 0, 0, 0, 0, 0, 0, 0, 0, 0, 0, 0,
            0, 0, 0, 0, 0, 0, 0, 0, 0, 0, 0, 0, 0, 0, 0, 0, 0, 0, 0, 0, 0, 0, 0, 0, 0, 0, 0, 0, 0, 0, 0, 0, 0, 0, 0, 0, 0, 0, 0, 0, 0, 0, 0, 0, 0, 0, 0, 0, 0, 0,
            0, 0, 0, 0, 0, 0, 0, 0, 0, 0, 0, 0, 0, 0, 0, 0, 0, 0, 0, 0, 0, 0, 0, 0, 0, 0, 0, 0, 0, 0, 0, 0, 0, 0, 0, 0, 0, 0, 0, 0, 0, 0, 0, 0, 0, 0, 0, 0, 0, 0,
            0, 0, 0, 0, 0, 0, 0, 0, 0, 0, 0, 0, 0, 0, 0, 0, 0, 0, 0, 0, 0, 0, 0, 0, 2001, 2002, 2042, 2003, 0, 0, 0, 0, 0, 0, 0, 0, 0, 0, 0, 0, 0, 0, 0, 0, 0, 0, 0, 0, 0, 0,
            0, 0, 0, 0, 0, 0, 0, 0, 0, 0, 0, 0, 0, 0, 0, 0, 0, 0, 0, 0, 0, 0, 0, 0, 0, 2049, 2050, 0, 0, 0, 0, 0, 0, 0, 2653, 2654, 2655, 2656, 0, 0, 0, 0, 0, 0, 0, 0, 0, 0, 0, 0,
            0, 0, 0, 0, 0, 0, 0, 0, 0, 0, 0, 0, 0, 0, 0, 0, 0, 0, 0, 0, 0, 0, 0, 0, 2089, 2057, 2058, 2059, 0, 0, 0, 0, 0, 0, 0, 0, 0, 0, 0, 0, 0, 0, 0, 0, 0, 0, 0, 0, 0, 0,
            0, 0, 0, 0, 0, 0, 0, 0, 0, 0, 0, 0, 0, 0, 0, 0, 0, 0, 0, 0, 0, 0, 0, 0, 0, 2017, 2018, 2019, 0, 0, 0, 0, 0, 0, 0, 0, 0, 0, 0, 0, 0, 0, 0, 0, 0, 0, 0, 0, 0, 0,
            0, 0, 0, 0, 0, 0, 0, 0, 0, 0, 0, 0, 0, 0, 0, 0, 0, 0, 0, 0, 0, 0, 0, 0, 0, 2025, 2026, 2027, 0, 0, 0, 0, 0, 0, 0, 0, 0, 0, 0, 0, 0, 0, 0, 0, 0, 0, 0, 0, 0, 0,
            0, 0, 0, 0, 0, 0, 0, 0, 0, 0, 0, 0, 0, 0, 0, 0, 0, 0, 0, 0, 0, 0, 0, 0, 0, 0, 0, 0, 0, 0, 0, 0, 0, 0, 0, 0, 0, 0, 0, 0, 0, 0, 0, 0, 0, 0, 0, 0, 0, 0,
            0, 0, 0, 0, 0, 0, 0, 0, 0, 0, 0, 0, 0, 0, 0, 0, 0, 0, 0, 0, 0, 0, 0, 0, 0, 0, 0, 0, 0, 0, 0, 0, 0, 0, 0, 0, 0, 0, 0, 0, 0, 0, 0, 0, 0, 0, 0, 0, 0, 0,
            0, 0, 0, 0, 0, 0, 0, 421, 422, 421, 422, 0, 0, 0, 0, 0, 0, 0, 0, 0, 0, 0, 0, 0, 2609, 2610, 2611, 2612, 2613, 0, 0, 0, 0, 0, 0, 0, 0, 0, 0, 0, 0, 0, 0, 0, 0, 0, 0, 0, 0, 0,
            0, 0, 0, 0, 0, 0, 0, 0, 0, 0, 0, 0, 421, 422, 0, 0, 0, 0, 0, 0, 0, 0, 0, 0, 0, 0, 0, 0, 0, 0, 0, 0, 0, 0, 0, 0, 0, 0, 0, 0, 0, 0, 0, 0, 0, 0, 0, 0, 0, 0,
            0, 0, 0, 0, 0, 0, 0, 0, 0, 0, 0, 0, 0, 0, 0, 0, 0, 0, 0, 0, 0, 0, 0, 0, 0, 0, 0, 0, 0, 0, 0, 0, 0, 0, 0, 0, 0, 0, 0, 0, 0, 0, 0, 0, 0, 0, 0, 0, 0, 0,
            0, 0, 0, 0, 0, 0, 0, 0, 0, 0, 0, 0, 0, 0, 0, 0, 0, 0, 0, 0, 0, 0, 0, 0, 0, 0, 0, 0, 0, 0, 0, 0, 0, 0, 0, 0, 0, 0, 0, 0, 0, 0, 0, 0, 0, 0, 0, 0, 0, 0,
            0, 0, 0, 0, 0, 0, 0, 0, 0, 0, 0, 0, 0, 0, 0, 0, 0, 0, 0, 0, 0, 0, 0, 0, 0, 0, 0, 0, 0, 0, 0, 0, 0, 0, 0, 0, 0, 0, 0, 0, 0, 0, 0, 0, 0, 0, 0, 0, 0, 0,
            0, 0, 0, 0, 0, 0, 0, 0, 0, 0, 0, 0, 0, 0, 0, 0, 0, 0, 0, 0, 0, 0, 0, 0, 0, 0, 0, 0, 0, 0, 0, 0, 0, 0, 0, 0, 0, 0, 0, 0, 0, 0, 0, 0, 0, 0, 0, 0, 0, 0,
            0, 0, 0, 0, 0, 0, 0, 0, 0, 0, 0, 0, 0, 0, 0, 0, 0, 0, 0, 0, 0, 0, 0, 0, 0, 0, 0, 0, 0, 0, 0, 0, 0, 0, 0, 0, 0, 0, 0, 0, 0, 0, 0, 0, 0, 0, 0, 0, 0, 0,
            0, 0, 0, 0, 0, 0, 0, 0, 0, 0, 0, 0, 0, 0, 0, 0, 0, 0, 0, 0, 0, 0, 0, 0, 0, 0, 0, 0, 0, 0, 0, 0, 0, 0, 0, 0, 0, 0, 0, 0, 0, 0, 0, 0, 0, 0, 0, 0, 0, 0,
            0, 0, 0, 0, 0, 0, 0, 0, 0, 0, 0, 0, 0, 0, 0, 0, 0, 0, 0, 0, 0, 0, 0, 0, 0, 0, 0, 0, 0, 0, 0, 0, 0, 0, 0, 0, 0, 0, 0, 0, 0, 0, 0, 0, 0, 0, 0, 0, 0, 0,
            0, 0, 0, 0, 0, 0, 0, 0, 0, 0, 0, 0, 0, 0, 0, 0, 0, 0, 0, 0, 0, 0, 0, 0, 0, 0, 0, 0, 0, 0, 0, 0, 0, 0, 0, 0, 0, 0, 0, 0, 0, 0, 0, 0, 0, 0, 0, 0, 0, 0,
            0, 0, 0, 0, 0, 0, 0, 0, 0, 0, 0, 0, 0, 0, 0, 0, 0, 0, 0, 0, 0, 0, 0, 0, 0, 0, 0, 0, 0, 0, 0, 0, 0, 0, 0, 0, 0, 0, 0, 0, 0, 0, 0, 0, 0, 0, 0, 0, 0, 0,
            0, 0, 0, 0, 0, 0, 421, 422, 421, 422, 421, 422, 421, 422, 0, 0, 0, 0, 0, 0, 0, 0, 0, 0, 0, 0, 0, 0, 0, 0, 0, 0, 0, 0, 0, 0, 0, 0, 0, 0, 0, 0, 0, 0, 0, 0, 0, 0, 0, 0,
            0, 0, 0, 0, 0, 0, 0, 0, 0, 0, 0, 0, 0, 0, 0, 0, 0, 0, 0, 0, 0, 0, 0, 0, 0, 0, 0, 0, 0, 0, 0, 0, 0, 0, 0, 0, 0, 0, 0, 0, 0, 0, 0, 0, 0, 0, 0, 0, 0, 0,
            0, 0, 0, 0, 0, 0, 0, 0, 0, 0, 0, 0, 0, 0, 421, 422, 421, 422, 421, 422, 421, 422, 0, 0, 0, 0, 421, 422, 421, 422, 421, 422, 421, 422, 421, 422, 421, 422, 421, 422, 421, 422, 0, 0, 0, 0, 0, 0, 0, 0,
            0, 0, 0, 0, 0, 0, 0, 0, 0, 0, 0, 0, 0, 0, 0, 0, 0, 0, 0, 0, 0, 0, 0, 0, 0, 0, 0, 0, 0, 0, 0, 0, 0, 0, 0, 0, 0, 0, 0, 0, 0, 0, 0, 0, 0, 0, 0, 0, 0, 0,
            0, 0, 0, 0, 0, 0, 0, 0, 0, 0, 0, 0, 0, 0, 0, 0, 0, 0, 0, 0, 0, 0, 0, 0, 0, 0, 0, 0, 0, 0, 0, 0, 0, 0, 0, 0, 0, 0, 0, 0, 0, 0, 0, 0, 0, 0, 0, 0, 0, 0,
            0, 0, 0, 0, 0, 0, 0, 0, 0, 0, 0, 0, 0, 0, 0, 0, 0, 0, 0, 0, 0, 0, 0, 0, 0, 0, 0, 0, 0, 0, 0, 0, 0, 0, 0, 0, 0, 0, 0, 0, 0, 0, 0, 0, 0, 0, 0, 0, 0, 0,
            0, 0, 0, 0, 0, 0, 0, 0, 0, 0, 0, 0, 0, 0, 0, 0, 0, 0, 0, 0, 0, 0, 0, 0, 0, 0, 0, 0, 0, 0, 0, 0, 0, 0, 0, 0, 0, 0, 0, 0, 0, 0, 0, 0, 0, 0, 0, 0, 0, 0],
         "height":40,
         "id":4,
         "name":"above",
         "opacity":1,
         "type":"tilelayer",
         "visible":true,
         "width":50,
         "x":0,
         "y":0
        }],
 "nextlayerid":7,
 "nextobjectid":12,
 "orientation":"orthogonal",
 "properties":[
        {
         "name":"region",
         "type":"string",
         "value":"viridian_city"
        }, 
        {
         "name":"world_x",
         "type":"int",
         "value":-6
        }, 
        {
         "name":"world_y",
         "type":"int",
         "value":-80
        }],
 "renderorder":"right-down",
 "tiledversion":"1.11.2",
 "tileheight":32,
 "tilesets":[
        {
         "columns":8,
         "firstgid":1,
         "image":"..\/tilesets\/Outside.png",
         "imageheight":16064,
         "imagewidth":256,
         "margin":0,
         "name":"Outside",
         "spacing":0,
         "tilecount":4016,
         "tileheight":32,
         "tilewidth":32
        }],
 "tilewidth":32,
 "type":"map",
 "version":"1.10",
 "width":50
}